MANIFEST.in
README.md
requirements.txt
setup.cfg
setup.py
version
agoge/__init__.py
agoge/data_handler.py
agoge/inference_worker.py
agoge/lmdb_helper.py
agoge/model.py
agoge/solver.py
agoge/train_worker.py
agoge/utils.py
agoge.egg-info/PKG-INFO
agoge.egg-info/SOURCES.txt
agoge.egg-info/dependency_links.txt
agoge.egg-info/requires.txt
agoge.egg-info/top_level.txt
agoge.egg-info/zip-safe