Metadata-Version: 2.1
Name: agoge
Version: 0.1.3
Summary: Machine Learning infra
Home-page: https://github.com/nintorac/agoge
Author: Nintorac
Author-email: agoge@nintorac.dev
License: MIT
Keywords: pytorch,machine learning
Platform: UNKNOWN
Classifier: Development Status :: 3 - Alpha
Classifier: Intended Audience :: Developers
Classifier: Topic :: Software Development :: Build Tools
Classifier: License :: OSI Approved :: MIT License
Classifier: Programming Language :: Python :: 3
Classifier: Programming Language :: Python :: 3.4
Classifier: Programming Language :: Python :: 3.5
Classifier: Programming Language :: Python :: 3.6
